aupostcodes.py
aupostcodes-0.1.1.dist-info/DESCRIPTION.rst
aupostcodes-0.1.1.dist-info/METADATA
aupostcodes-0.1.1.dist-info/RECORD
aupostcodes-0.1.1.dist-info/WHEEL
aupostcodes-0.1.1.dist-info/metadata.json
aupostcodes-0.1.1.dist-info/top_level.txt
